[
  {
    "id": "038b95c5-161e-494b-a309-5d8952051e60",
    "stat_date": "2026-03-24",
    "total_users": 5462,
    "active_users_30d": 917,
    "new_users_today": 5,
    "retention_pct": 16.79,
    "referral_pct": 94.56,
    "daily_transaction_volume": 1488023,
    "users_by_role": "{\"ceo\": 2, \"cfo\": 2, \"cmo\": 1, \"coo\": 3, \"crm\": 1, \"cto\": 3, \"agent\": 5406, \"tenant\": 5404, \"manager\": 18, \"employee\": 3, \"landlord\": 5405, \"supporter\": 245, \"operations\": 5, \"super_admin\": 5}",
    "created_at": "2026-03-24 00:00:00.019088+00",
    "updated_at": "2026-03-24 20:00:00.020999+00"
  },
  {
    "id": "3af96ca0-1472-4dd5-a28d-ca73302cc703",
    "stat_date": "2026-03-18",
    "total_users": 5439,
    "active_users_30d": 3085,
    "new_users_today": 44,
    "retention_pct": 56.72,
    "referral_pct": 94.89,
    "daily_transaction_volume": 2044562,
    "users_by_role": "{\"ceo\": 1, \"cfo\": 1, \"cmo\": 1, \"coo\": 3, \"crm\": 1, \"cto\": 2, \"agent\": 5382, \"tenant\": 5381, \"manager\": 17, \"employee\": 2, \"landlord\": 5382, \"supporter\": 210, \"operations\": 4, \"super_admin\": 4}",
    "created_at": "2026-03-18 00:00:00.020867+00",
    "updated_at": "2026-03-18 20:00:00.026366+00"
  },
  {
    "id": "1e4875ad-ee27-4140-831c-cf7d790acc81",
    "stat_date": "2026-03-13",
    "total_users": 5337,
    "active_users_30d": 3839,
    "new_users_today": 17,
    "retention_pct": 71.93,
    "referral_pct": 96.53,
    "daily_transaction_volume": 48534,
    "users_by_role": "{\"ceo\": 1, \"cfo\": 1, \"cmo\": 1, \"coo\": 3, \"crm\": 1, \"cto\": 2, \"agent\": 5312, \"tenant\": 5309, \"manager\": 16, \"employee\": 2, \"landlord\": 5308, \"supporter\": 85, \"operations\": 2, \"super_admin\": 2}",
    "created_at": "2026-03-13 08:56:01.776843+00",
    "updated_at": "2026-03-13 20:00:00.021716+00"
  },
  {
    "id": "3f9b612c-ffbf-45b7-b90c-f25496ad099b",
    "stat_date": "2026-03-16",
    "total_users": 5368,
    "active_users_30d": 3042,
    "new_users_today": 25,
    "retention_pct": 56.67,
    "referral_pct": 96.11,
    "daily_transaction_volume": 2000,
    "users_by_role": "{\"ceo\": 1, \"cfo\": 1, \"cmo\": 1, \"coo\": 3, \"crm\": 1, \"cto\": 2, \"agent\": 5333, \"tenant\": 5331, \"manager\": 16, \"employee\": 2, \"landlord\": 5331, \"supporter\": 127, \"operations\": 3, \"super_admin\": 2}",
    "created_at": "2026-03-16 00:00:00.019516+00",
    "updated_at": "2026-03-16 20:00:00.020711+00"
  },
  {
    "id": "cf1c2cbe-c82b-464a-b0a1-de6265552126",
    "stat_date": "2026-03-20",
    "total_users": 5445,
    "active_users_30d": 2237,
    "new_users_today": 0,
    "retention_pct": 41.08,
    "referral_pct": 94.78,
    "daily_transaction_volume": 135000,
    "users_by_role": "{\"ceo\": 2, \"cfo\": 1, \"cmo\": 1, \"coo\": 3, \"crm\": 1, \"cto\": 2, \"agent\": 5389, \"tenant\": 5387, \"manager\": 17, \"employee\": 2, \"landlord\": 5388, \"supporter\": 219, \"operations\": 5, \"super_admin\": 4}",
    "created_at": "2026-03-20 00:00:00.017123+00",
    "updated_at": "2026-03-20 20:00:00.01674+00"
  },
  {
    "id": "e09dc243-efea-4150-8e01-04c566f55ae8",
    "stat_date": "2026-03-14",
    "total_users": 5340,
    "active_users_30d": 3246,
    "new_users_today": 2,
    "retention_pct": 60.79,
    "referral_pct": 96.48,
    "daily_transaction_volume": 95062,
    "users_by_role": "{\"ceo\": 1, \"cfo\": 1, \"cmo\": 1, \"coo\": 3, \"crm\": 1, \"cto\": 2, \"agent\": 5315, \"tenant\": 5312, \"manager\": 16, \"employee\": 2, \"landlord\": 5311, \"supporter\": 91, \"operations\": 3, \"super_admin\": 2}",
    "created_at": "2026-03-14 00:00:00.021372+00",
    "updated_at": "2026-03-14 20:00:00.020964+00"
  },
  {
    "id": "6fca6ce5-dab4-46c5-8adb-0eabd5da0045",
    "stat_date": "2026-03-23",
    "total_users": 5457,
    "active_users_30d": 1036,
    "new_users_today": 4,
    "retention_pct": 18.98,
    "referral_pct": 94.61,
    "daily_transaction_volume": 1172150,
    "users_by_role": "{\"ceo\": 2, \"cfo\": 2, \"cmo\": 1, \"coo\": 3, \"crm\": 1, \"cto\": 3, \"agent\": 5401, \"tenant\": 5399, \"manager\": 18, \"employee\": 3, \"landlord\": 5400, \"supporter\": 239, \"operations\": 5, \"super_admin\": 5}",
    "created_at": "2026-03-23 00:00:00.024193+00",
    "updated_at": "2026-03-23 20:00:00.016933+00"
  },
  {
    "id": "a5be87dd-3f55-473f-887f-3dd7b3e38177",
    "stat_date": "2026-03-17",
    "total_users": 5396,
    "active_users_30d": 3055,
    "new_users_today": 28,
    "retention_pct": 56.62,
    "referral_pct": 95.63,
    "daily_transaction_volume": 3021734,
    "users_by_role": "{\"ceo\": 1, \"cfo\": 1, \"cmo\": 1, \"coo\": 3, \"crm\": 1, \"cto\": 2, \"agent\": 5339, \"tenant\": 5338, \"manager\": 16, \"employee\": 2, \"landlord\": 5337, \"supporter\": 162, \"operations\": 3, \"super_admin\": 2}",
    "created_at": "2026-03-17 00:00:00.020916+00",
    "updated_at": "2026-03-17 20:00:00.020758+00"
  },
  {
    "id": "0c3b8dcb-c6aa-442a-ae38-d12ebbc27736",
    "stat_date": "2026-03-15",
    "total_users": 5344,
    "active_users_30d": 3048,
    "new_users_today": 4,
    "retention_pct": 57.04,
    "referral_pct": 96.46,
    "daily_transaction_volume": 1935,
    "users_by_role": "{\"ceo\": 1, \"cfo\": 1, \"cmo\": 1, \"coo\": 3, \"crm\": 1, \"cto\": 2, \"agent\": 5319, \"tenant\": 5316, \"manager\": 16, \"employee\": 2, \"landlord\": 5315, \"supporter\": 99, \"operations\": 3, \"super_admin\": 2}",
    "created_at": "2026-03-15 00:00:00.017644+00",
    "updated_at": "2026-03-15 20:00:00.021562+00"
  },
  {
    "id": "4483181d-fe1f-49c6-bd66-c032e5f4f72a",
    "stat_date": "2026-03-19",
    "total_users": 5444,
    "active_users_30d": 2444,
    "new_users_today": 4,
    "retention_pct": 44.89,
    "referral_pct": 94.8,
    "daily_transaction_volume": 177934,
    "users_by_role": "{\"ceo\": 1, \"cfo\": 1, \"cmo\": 1, \"coo\": 3, \"crm\": 1, \"cto\": 2, \"agent\": 5388, \"tenant\": 5386, \"manager\": 17, \"employee\": 2, \"landlord\": 5387, \"supporter\": 217, \"operations\": 5, \"super_admin\": 4}",
    "created_at": "2026-03-19 00:00:00.020465+00",
    "updated_at": "2026-03-19 20:00:00.019991+00"
  },
  {
    "id": "df297f84-810c-44a5-b6df-674ff3835026",
    "stat_date": "2026-03-22",
    "total_users": 5453,
    "active_users_30d": 1129,
    "new_users_today": 3,
    "retention_pct": 20.7,
    "referral_pct": 94.65,
    "daily_transaction_volume": 0,
    "users_by_role": "{\"ceo\": 2, \"cfo\": 2, \"cmo\": 1, \"coo\": 3, \"crm\": 1, \"cto\": 3, \"agent\": 5397, \"tenant\": 5395, \"manager\": 18, \"employee\": 3, \"landlord\": 5396, \"supporter\": 234, \"operations\": 5, \"super_admin\": 5}",
    "created_at": "2026-03-22 00:00:00.019725+00",
    "updated_at": "2026-03-22 20:00:00.021316+00"
  },
  {
    "id": "39278500-537d-4c28-b1e8-1082d2b334d8",
    "stat_date": "2026-03-21",
    "total_users": 5450,
    "active_users_30d": 1623,
    "new_users_today": 4,
    "retention_pct": 29.78,
    "referral_pct": 94.7,
    "daily_transaction_volume": 20000,
    "users_by_role": "{\"ceo\": 2, \"cfo\": 2, \"cmo\": 1, \"coo\": 3, \"crm\": 1, \"cto\": 3, \"agent\": 5394, \"tenant\": 5392, \"manager\": 18, \"employee\": 3, \"landlord\": 5393, \"supporter\": 228, \"operations\": 5, \"super_admin\": 5}",
    "created_at": "2026-03-21 00:00:00.020329+00",
    "updated_at": "2026-03-21 20:00:00.024145+00"
  },
  {
    "id": "df59ded3-6f42-4d56-80ce-b480b1ccdca0",
    "stat_date": "2026-03-25",
    "total_users": 5661,
    "active_users_30d": 1013,
    "new_users_today": 199,
    "retention_pct": 17.89,
    "referral_pct": 91.43,
    "daily_transaction_volume": 50116896,
    "users_by_role": "{\"ceo\": 2, \"cfo\": 2, \"cmo\": 1, \"coo\": 3, \"crm\": 1, \"cto\": 3, \"agent\": 5607, \"tenant\": 5605, \"manager\": 18, \"employee\": 3, \"landlord\": 5604, \"supporter\": 437, \"operations\": 5, \"super_admin\": 5}",
    "created_at": "2026-03-25 00:00:00.029376+00",
    "updated_at": "2026-03-25 20:00:00.021017+00"
  },
  {
    "id": "765dc567-c2bb-481f-b4e3-4033090c9528",
    "stat_date": "2026-03-27",
    "total_users": 5661,
    "active_users_30d": 946,
    "new_users_today": 4,
    "retention_pct": 16.71,
    "referral_pct": 91.38,
    "daily_transaction_volume": 240000,
    "users_by_role": "{\"ceo\": 2, \"cfo\": 2, \"cmo\": 1, \"coo\": 3, \"crm\": 1, \"cto\": 3, \"agent\": 5608, \"tenant\": 5606, \"manager\": 17, \"employee\": 2, \"landlord\": 5605, \"supporter\": 441, \"operations\": 4, \"super_admin\": 5}",
    "created_at": "2026-03-27 00:00:00.030369+00",
    "updated_at": "2026-03-27 20:00:00.026405+00"
  },
  {
    "id": "8d289540-225b-4a7d-83b7-489d6e989896",
    "stat_date": "2026-03-26",
    "total_users": 5657,
    "active_users_30d": 972,
    "new_users_today": 8,
    "retention_pct": 17.18,
    "referral_pct": 91.44,
    "daily_transaction_volume": 998056,
    "users_by_role": "{\"ceo\": 2, \"cfo\": 2, \"cmo\": 1, \"coo\": 3, \"crm\": 1, \"cto\": 3, \"agent\": 5604, \"tenant\": 5602, \"manager\": 16, \"employee\": 2, \"landlord\": 5601, \"supporter\": 437, \"operations\": 4, \"super_admin\": 5}",
    "created_at": "2026-03-26 00:00:00.033247+00",
    "updated_at": "2026-03-26 20:00:00.026086+00"
  },
  {
    "id": "efaefe26-546d-4afb-a639-8cf88b1984b0",
    "stat_date": "2026-03-29",
    "total_users": 5694,
    "active_users_30d": 868,
    "new_users_today": 32,
    "retention_pct": 15.24,
    "referral_pct": 91.32,
    "daily_transaction_volume": 30000,
    "users_by_role": "{\"ceo\": 2, \"cfo\": 2, \"cmo\": 1, \"coo\": 3, \"crm\": 1, \"cto\": 3, \"agent\": 5641, \"tenant\": 5639, \"manager\": 17, \"employee\": 2, \"landlord\": 5638, \"supporter\": 474, \"operations\": 4, \"super_admin\": 5}",
    "created_at": "2026-03-29 00:00:00.02951+00",
    "updated_at": "2026-03-29 20:00:00.021223+00"
  },
  {
    "id": "40972a54-5419-4b4d-9547-08d036425af6",
    "stat_date": "2026-03-28",
    "total_users": 5662,
    "active_users_30d": 879,
    "new_users_today": 1,
    "retention_pct": 15.52,
    "referral_pct": 91.36,
    "daily_transaction_volume": 656250,
    "users_by_role": "{\"ceo\": 2, \"cfo\": 2, \"cmo\": 1, \"coo\": 3, \"crm\": 1, \"cto\": 3, \"agent\": 5609, \"tenant\": 5607, \"manager\": 17, \"employee\": 2, \"landlord\": 5606, \"supporter\": 442, \"operations\": 4, \"super_admin\": 5}",
    "created_at": "2026-03-28 00:00:00.031149+00",
    "updated_at": "2026-03-28 20:00:00.020423+00"
  },
  {
    "id": "7b245f16-507d-4f29-9923-2cd9da1322a6",
    "stat_date": "2026-03-30",
    "total_users": 5702,
    "active_users_30d": 827,
    "new_users_today": 8,
    "retention_pct": 14.5,
    "referral_pct": 91.21,
    "daily_transaction_volume": 1366061,
    "users_by_role": "{\"ceo\": 2, \"cfo\": 3, \"cmo\": 1, \"coo\": 3, \"crm\": 1, \"cto\": 4, \"agent\": 5649, \"tenant\": 5647, \"manager\": 18, \"employee\": 2, \"landlord\": 5646, \"supporter\": 482, \"operations\": 4, \"super_admin\": 6}",
    "created_at": "2026-03-30 00:00:00.032+00",
    "updated_at": "2026-03-30 20:00:00.026292+00"
  },
  {
    "id": "7956c7fb-f494-4759-93f9-39df31c18ac8",
    "stat_date": "2026-04-07",
    "total_users": 5739,
    "active_users_30d": 666,
    "new_users_today": 0,
    "retention_pct": 11.6,
    "referral_pct": 90.61,
    "daily_transaction_volume": 0,
    "users_by_role": "{\"ceo\": 2, \"cfo\": 4, \"cmo\": 1, \"coo\": 3, \"crm\": 1, \"cto\": 5, \"agent\": 5668, \"tenant\": 5665, \"manager\": 18, \"employee\": 4, \"landlord\": 5665, \"supporter\": 530, \"operations\": 8, \"super_admin\": 6}",
    "created_at": "2026-04-07 02:00:00.019389+00",
    "updated_at": "2026-04-07 02:00:00.019389+00"
  },
  {
    "id": "ffd5b00f-5005-49f1-af3e-f82ec77c6bdb",
    "stat_date": "2026-04-08",
    "total_users": 5745,
    "active_users_30d": 665,
    "new_users_today": 0,
    "retention_pct": 11.58,
    "referral_pct": 90.51,
    "daily_transaction_volume": 0,
    "users_by_role": "{\"ceo\": 2, \"cfo\": 5, \"cmo\": 1, \"coo\": 3, \"crm\": 1, \"cto\": 5, \"agent\": 5672, \"tenant\": 5670, \"manager\": 18, \"employee\": 4, \"landlord\": 5670, \"supporter\": 536, \"operations\": 8, \"super_admin\": 6}",
    "created_at": "2026-04-08 02:00:00.021971+00",
    "updated_at": "2026-04-08 02:00:00.021971+00"
  },
  {
    "id": "7be1af18-b9b2-478b-b7b6-389fabad1be2",
    "stat_date": "2026-04-09",
    "total_users": 5762,
    "active_users_30d": 675,
    "new_users_today": 0,
    "retention_pct": 11.71,
    "referral_pct": 90.25,
    "daily_transaction_volume": 0,
    "users_by_role": "{\"ceo\": 2, \"cfo\": 6, \"cmo\": 1, \"coo\": 3, \"crm\": 1, \"cto\": 5, \"agent\": 5681, \"tenant\": 5681, \"manager\": 18, \"employee\": 4, \"landlord\": 5679, \"supporter\": 559, \"operations\": 8, \"super_admin\": 6}",
    "created_at": "2026-04-09 02:00:00.027699+00",
    "updated_at": "2026-04-09 02:00:00.027699+00"
  },
  {
    "id": "0ed3fa3e-ad2d-4e2d-a4a7-638587cbe846",
    "stat_date": "2026-04-10",
    "total_users": 5787,
    "active_users_30d": 683,
    "new_users_today": 0,
    "retention_pct": 11.8,
    "referral_pct": 89.93,
    "daily_transaction_volume": 0,
    "users_by_role": "{\"ceo\": 2, \"cfo\": 6, \"cmo\": 1, \"coo\": 3, \"crm\": 1, \"cto\": 5, \"agent\": 5696, \"tenant\": 5695, \"manager\": 18, \"employee\": 8, \"landlord\": 5693, \"supporter\": 577, \"operations\": 8, \"super_admin\": 5}",
    "created_at": "2026-04-10 02:00:00.043097+00",
    "updated_at": "2026-04-10 02:00:00.043097+00"
  },
  {
    "id": "d4e29783-38be-4cf2-8b23-9c2f0d33b6a9",
    "stat_date": "2026-03-31",
    "total_users": 5713,
    "active_users_30d": 799,
    "new_users_today": 12,
    "retention_pct": 13.99,
    "referral_pct": 91.02,
    "daily_transaction_volume": 53293000,
    "users_by_role": "{\"ceo\": 2, \"cfo\": 3, \"cmo\": 1, \"coo\": 3, \"crm\": 1, \"cto\": 5, \"agent\": 5658, \"tenant\": 5656, \"manager\": 17, \"employee\": 4, \"landlord\": 5655, \"supporter\": 495, \"operations\": 6, \"super_admin\": 7}",
    "created_at": "2026-03-31 00:00:00.02189+00",
    "updated_at": "2026-03-31 20:00:00.020735+00"
  },
  {
    "id": "f3f5e309-39ee-4d94-bfbc-39f59dfa453e",
    "stat_date": "2026-04-11",
    "total_users": 5798,
    "active_users_30d": 682,
    "new_users_today": 0,
    "retention_pct": 11.76,
    "referral_pct": 89.86,
    "daily_transaction_volume": 0,
    "users_by_role": "{\"ceo\": 2, \"cfo\": 7, \"cmo\": 1, \"coo\": 3, \"crm\": 1, \"cto\": 5, \"agent\": 5708, \"tenant\": 5706, \"manager\": 18, \"employee\": 8, \"landlord\": 5705, \"supporter\": 587, \"operations\": 8, \"super_admin\": 6}",
    "created_at": "2026-04-11 02:00:00.04063+00",
    "updated_at": "2026-04-11 02:00:00.04063+00"
  },
  {
    "id": "f05a6703-5b00-42d4-a879-098047d1c272",
    "stat_date": "2026-04-12",
    "total_users": 5801,
    "active_users_30d": 671,
    "new_users_today": 0,
    "retention_pct": 11.57,
    "referral_pct": 89.81,
    "daily_transaction_volume": 0,
    "users_by_role": "{\"ceo\": 2, \"cfo\": 7, \"cmo\": 1, \"coo\": 3, \"crm\": 1, \"cto\": 5, \"agent\": 5711, \"tenant\": 5709, \"manager\": 18, \"employee\": 8, \"landlord\": 5708, \"supporter\": 590, \"operations\": 8, \"super_admin\": 6}",
    "created_at": "2026-04-12 02:00:00.043896+00",
    "updated_at": "2026-04-12 02:00:00.043896+00"
  },
  {
    "id": "790eacb1-08c5-467d-8859-00d6a5a545cd",
    "stat_date": "2026-04-13",
    "total_users": 5803,
    "active_users_30d": 660,
    "new_users_today": 0,
    "retention_pct": 11.37,
    "referral_pct": 89.78,
    "daily_transaction_volume": 0,
    "users_by_role": "{\"ceo\": 2, \"cfo\": 7, \"cmo\": 1, \"coo\": 3, \"crm\": 1, \"cto\": 5, \"agent\": 5713, \"tenant\": 5711, \"manager\": 18, \"employee\": 8, \"landlord\": 5710, \"supporter\": 592, \"operations\": 8, \"super_admin\": 6}",
    "created_at": "2026-04-13 02:00:00.016313+00",
    "updated_at": "2026-04-13 02:00:00.016313+00"
  },
  {
    "id": "63df2e93-bad9-4b0e-8f97-bfbddecc95ef",
    "stat_date": "2026-04-01",
    "total_users": 5718,
    "active_users_30d": 772,
    "new_users_today": 5,
    "retention_pct": 13.5,
    "referral_pct": 90.94,
    "daily_transaction_volume": 26094722,
    "users_by_role": "{\"ceo\": 2, \"cfo\": 4, \"cmo\": 1, \"coo\": 3, \"crm\": 1, \"cto\": 5, \"agent\": 5659, \"tenant\": 5657, \"manager\": 17, \"employee\": 4, \"landlord\": 5656, \"supporter\": 499, \"operations\": 7, \"super_admin\": 7}",
    "created_at": "2026-04-01 00:00:00.02954+00",
    "updated_at": "2026-04-01 20:00:00.021629+00"
  },
  {
    "id": "d84265fc-ddd0-455b-a1f4-c42ccf69c856",
    "stat_date": "2026-04-02",
    "total_users": 5718,
    "active_users_30d": 701,
    "new_users_today": 0,
    "retention_pct": 12.26,
    "referral_pct": 90.94,
    "daily_transaction_volume": 60000,
    "users_by_role": "{\"ceo\": 2, \"cfo\": 4, \"cmo\": 1, \"coo\": 3, \"crm\": 1, \"cto\": 5, \"agent\": 5659, \"tenant\": 5657, \"manager\": 17, \"employee\": 4, \"landlord\": 5656, \"supporter\": 499, \"operations\": 7, \"super_admin\": 7}",
    "created_at": "2026-04-02 00:00:00.022387+00",
    "updated_at": "2026-04-02 04:00:00.021311+00"
  },
  {
    "id": "c629af5c-f225-49c7-a19d-a6d705ca9ec6",
    "stat_date": "2026-04-03",
    "total_users": 5727,
    "active_users_30d": 698,
    "new_users_today": 0,
    "retention_pct": 12.19,
    "referral_pct": 90.8,
    "daily_transaction_volume": 0,
    "users_by_role": "{\"ceo\": 2, \"cfo\": 4, \"cmo\": 1, \"coo\": 3, \"crm\": 1, \"cto\": 5, \"agent\": 5658, \"tenant\": 5656, \"manager\": 18, \"employee\": 4, \"landlord\": 5656, \"supporter\": 514, \"operations\": 8, \"super_admin\": 7}",
    "created_at": "2026-04-03 02:00:00.017025+00",
    "updated_at": "2026-04-03 02:00:00.017025+00"
  },
  {
    "id": "b3a4c50c-8d2a-44a0-9378-8b3c8452e883",
    "stat_date": "2026-04-04",
    "total_users": 5729,
    "active_users_30d": 686,
    "new_users_today": 0,
    "retention_pct": 11.97,
    "referral_pct": 90.77,
    "daily_transaction_volume": 0,
    "users_by_role": "{\"ceo\": 2, \"cfo\": 4, \"cmo\": 1, \"coo\": 3, \"crm\": 1, \"cto\": 5, \"agent\": 5657, \"tenant\": 5655, \"manager\": 18, \"employee\": 4, \"landlord\": 5655, \"supporter\": 518, \"operations\": 8, \"super_admin\": 6}",
    "created_at": "2026-04-04 02:00:00.013995+00",
    "updated_at": "2026-04-04 02:00:00.013995+00"
  },
  {
    "id": "08622ab1-f9d0-48a8-b300-a8364600e9be",
    "stat_date": "2026-04-05",
    "total_users": 5736,
    "active_users_30d": 680,
    "new_users_today": 0,
    "retention_pct": 11.85,
    "referral_pct": 90.66,
    "daily_transaction_volume": 0,
    "users_by_role": "{\"ceo\": 2, \"cfo\": 4, \"cmo\": 1, \"coo\": 3, \"crm\": 1, \"cto\": 5, \"agent\": 5665, \"tenant\": 5662, \"manager\": 18, \"employee\": 4, \"landlord\": 5662, \"supporter\": 527, \"operations\": 8, \"super_admin\": 6}",
    "created_at": "2026-04-05 02:00:00.042543+00",
    "updated_at": "2026-04-05 02:00:00.042543+00"
  },
  {
    "id": "c68d0bbb-c1d7-484b-9445-d126a3cd2371",
    "stat_date": "2026-04-06",
    "total_users": 5736,
    "active_users_30d": 669,
    "new_users_today": 0,
    "retention_pct": 11.66,
    "referral_pct": 90.66,
    "daily_transaction_volume": 0,
    "users_by_role": "{\"ceo\": 2, \"cfo\": 4, \"cmo\": 1, \"coo\": 3, \"crm\": 1, \"cto\": 5, \"agent\": 5665, \"tenant\": 5662, \"manager\": 18, \"employee\": 4, \"landlord\": 5662, \"supporter\": 527, \"operations\": 8, \"super_admin\": 6}",
    "created_at": "2026-04-06 02:00:00.031519+00",
    "updated_at": "2026-04-06 02:00:00.031519+00"
  }
]